brsus/__init__.py
brsus/interfaces/dataset.py
brsus/sim/__init__.py
brsus/sim/dataset.py
brsus/sim/download.py
brsus/toolbox/dbf.py
brsus/toolbox/ftp.py
brsus-0.0.1.dist-info/entry_points.txt
brsus-0.0.1.dist-info/WHEEL
brsus-0.0.1.dist-info/METADATA
brsus-0.0.1.dist-info/RECORD
